{
  "lastMsgId": 95921,
  "pending": {
    "mrdcq9wm3bn": {
      "dir": "out",
      "amtUzs": 46500,
      "place": "OOO YANDEXGO UB, UZ",
      "rawBalance": 1869866,
      "date": "09.07.2026",
      "title": "E-Com oplata",
      "card4": "5893",
      "step": "note",
      "askedAt": 1783592174758,
      "kind": "personal"
    }
  },
  "resolved": [
    {
      "date": "08.07.2026",
      "dir": "out",
      "amt": 26000
    },
    {
      "date": "08.07.2026",
      "dir": "out",
      "amt": 42000
    },
    {
      "date": "08.07.2026",
      "dir": "out",
      "amt": 275000
    },
    {
      "date": "08.07.2026",
      "dir": "in",
      "amt": 300000
    },
    {
      "date": "08.07.2026",
      "dir": "out",
      "amt": 1015
    },
    {
      "date": "08.07.2026",
      "dir": "out",
      "amt": 1207500
    },
    {
      "date": "08.07.2026",
      "dir": "out",
      "amt": 25000
    },
    {
      "date": "08.07.2026",
      "dir": "out",
      "amt": 225000
    },
    {
      "date": "08.07.2026",
      "dir": "out",
      "amt": 30000
    },
    {
      "date": "08.07.2026",
      "dir": "in",
      "amt": 2400000
    },
    {
      "date": "09.07.2026",
      "dir": "out",
      "amt": 186024
    },
    {
      "date": "09.07.2026",
      "dir": "out",
      "amt": 67737
    }
  ],
  "lastBalances": {
    "5893": 1869866
  },
  "lastReconcileDate": "08.07.2026"
}